watchui/__init__.py
watchui/__main__.py
watch_ui-0.0.9.dist-info/LICENSE
watch_ui-0.0.9.dist-info/METADATA
watch_ui-0.0.9.dist-info/WHEEL
watch_ui-0.0.9.dist-info/entry_points.txt
watch_ui-0.0.9.dist-info/top_level.txt
watch_ui-0.0.9.dist-info/RECORD
