Metadata-Version: 2.1
Name: watch-ui
Version: 0.0.9
Summary: autocompiling script for ui and qrc files for PySide2 and PyQt5
Home-page: https://github.com/mugiseyebrows/watch-ui
Author: Stanislav Doronin
Author-email: mugisbrows@gmail.com
License: UNKNOWN
Platform: UNKNOWN
Requires-Dist: eventloop
Requires-Dist: colorama
